torii/__init__.py
torii/_typing.py
torii/py.typed
torii/back/__init__.py
torii/back/cxxrtl.py
torii/back/rtlil.py
torii/back/verilog.py
torii/build/__init__.py
torii/build/dsl.py
torii/build/plat.py
torii/build/res.py
torii/build/run.py
torii/diagnostics/__init__.py
torii/diagnostics/errors.py
torii/diagnostics/warnings.py
torii/hdl/__init__.py
torii/hdl/_unused.py
torii/hdl/ast.py
torii/hdl/cd.py
torii/hdl/dsl.py
torii/hdl/ir.py
torii/hdl/mem.py
torii/hdl/rec.py
torii/hdl/xfrm.py
torii/lib/__init__.py
torii/lib/cdc.py
torii/lib/fifo.py
torii/lib/formal.py
torii/lib/io.py
torii/lib/scheduler.py
torii/lib/bus/__init__.py
torii/lib/bus/wishbone/__init__.py
torii/lib/coding/__init__.py
torii/lib/coding/cobs.py
torii/lib/coding/gray.py
torii/lib/coding/one_hot.py
torii/lib/coding/priority.py
torii/lib/mem/__init__.py
torii/lib/mem/map.py
torii/lib/soc/__init__.py
torii/lib/soc/event.py
torii/lib/soc/memory.py
torii/lib/soc/periph.py
torii/lib/soc/csr/__init__.py
torii/lib/soc/csr/bus.py
torii/lib/soc/csr/event.py
torii/lib/soc/csr/wishbone.py
torii/lib/soc/wishbone/__init__.py
torii/lib/soc/wishbone/bus.py
torii/lib/stdio/__init__.py
torii/lib/stdio/serial.py
torii/lib/stream/__init__.py
torii/lib/stream/simple.py
torii/lib/vendor/__init__.py
torii/lib/vendor/lattice/__init__.py
torii/lib/vendor/lattice/ice40.py
torii/lib/vendor/xilinx/__init__.py
torii/platform/__init__.py
torii/platform/formal.py
torii/platform/resources/__init__.py
torii/platform/resources/display.py
torii/platform/resources/interface.py
torii/platform/resources/memory.py
torii/platform/resources/user.py
torii/platform/resources/extensions/__init__.py
torii/platform/resources/extensions/pmod.py
torii/platform/vendor/__init__.py
torii/platform/vendor/altera.py
torii/platform/vendor/gowin.py
torii/platform/vendor/quicklogic.py
torii/platform/vendor/xilinx.py
torii/platform/vendor/lattice/__init__.py
torii/platform/vendor/lattice/ecp5.py
torii/platform/vendor/lattice/ice40.py
torii-0.8.1.dist-info/licenses/LICENSE
torii-0.8.1.dist-info/METADATA
torii-0.8.1.dist-info/WHEEL
torii-0.8.1.dist-info/top_level.txt
torii-0.8.1.dist-info/zip-safe
torii-0.8.1.dist-info/RECORD
