Metadata-Version: 2.4
Name: torii
Version: 0.8.1
Summary: Torii hardware definition language
Home-page: https://torii.shmdn.link/
Author: Aki Van Ness, Rachel Mant
Author-email: aki@lethalbit.net, git@dragonmux.network
License: BSD-2-Clause
Project-URL: Documentation, https://torii.shmdn.link/
Project-URL: Source Code, https://github.com/shrine-maiden-heavy-industries/torii-hdl
Project-URL: Bug Tracker, https://github.com/shrine-maiden-heavy-industries/torii-hdl/issues
Classifier: Development Status :: 4 - Beta
Classifier: Intended Audience :: Developers
Classifier: Intended Audience :: Information Technology
Classifier: Intended Audience :: Science/Research
Classifier: License :: OSI Approved :: BSD License
Classifier: Operating System :: MacOS :: MacOS X
Classifier: Operating System :: Microsoft :: Windows
Classifier: Operating System :: POSIX :: Linux
Classifier: Programming Language :: Python :: 3.10
Classifier: Programming Language :: Python :: 3.11
Classifier: Programming Language :: Python :: 3.12
Classifier: Programming Language :: Python :: 3.13
Classifier: Topic :: Scientific/Engineering
Classifier: Topic :: Scientific/Engineering :: Electronic Design Automation (EDA)
Classifier: Topic :: Software Development
Classifier: Topic :: Software Development :: Embedded Systems
Classifier: Topic :: Software Development :: Libraries
Classifier: Typing :: Typed
Requires-Python: ~=3.10
License-File: LICENSE
Requires-Dist: setuptools
Requires-Dist: pyvcd<0.5,>=0.4.0
Requires-Dist: Jinja2~=3.0
Requires-Dist: rich
Requires-Dist: typing-extensions; python_version < "3.12"
Provides-Extra: dev
Requires-Dist: nox; extra == "dev"
Dynamic: author
Dynamic: author-email
Dynamic: classifier
Dynamic: description
Dynamic: description-content-type
Dynamic: home-page
Dynamic: license
Dynamic: license-file
Dynamic: project-url
Dynamic: provides-extra
Dynamic: requires-dist
Dynamic: requires-python
Dynamic: summary
